{
  "logConfig": {
      "console": {
        "level": "info",
        "colorize": true
      },
      "rollingFile": {
        "level": "info",
        "datePattern" : ".yyyy-MM-dd",
        "filename": "application.log",
        "colorize": true
      },
      "email": {
        "host": "",//"smtp.gmail.com",
        "port": "",//"465",
        "ssl": true,
        "to": "aqaujsadmin@equninix.com",
        "from": "aqaujsadmin@equninix.com",
        "username": "",
        "password": "",
        "subject": "AquaJS Error:",
        "level": "error"
      }
  }
}